lxcat_data_parser/__init__.py
lxcat_data_parser/import_tools.py
lxcat_data_parser-0.1.0.dist-info/LICENSE
lxcat_data_parser-0.1.0.dist-info/METADATA
lxcat_data_parser-0.1.0.dist-info/WHEEL
lxcat_data_parser-0.1.0.dist-info/top_level.txt
lxcat_data_parser-0.1.0.dist-info/RECORD
