Metadata-Version: 2.1
Name: lxcat-data-parser
Version: 0.1.0
Summary: A set of tools for importing data from the LXcat project.
Home-page: https://gitlab.com/ethz_hvl/lxcat_data_parser/
Author: Alise Chachereau
Author-email: alisec@ethz.ch
License: GNU General Public License v3
Platform: UNKNOWN
Classifier: Programming Language :: Python :: 3.7
Classifier: Topic :: Scientific/Engineering :: Physics
Requires-Dist: pandas
